[
  {
    "nombre": "Cerveza Pilsen",
    "id": 10,
    "precio": 9.0,
    "cantidad": 382
  },
  {
    "nombre": "Takis",
    "id": 3,
    "precio": 3.0,
    "cantidad": 478
  },
  {
    "nombre": "Fortin Etiqueta Negra",
    "id": 6,
    "precio": 6.0,
    "cantidad": 293
  },
  {
    "nombre": "Galletitas Tortuguita",
    "id": 4,
    "precio": 6.0,
    "cantidad": 492
  },
  {
    "nombre": "Ron Fortin Frutos Rojos",
    "id": 11,
    "precio": 9.0,
    "cantidad": 138
  },
  {
    "nombre": "Fanta",
    "id": 5,
    "precio": 10.0,
    "cantidad": 230
  },
  {
    "nombre": "Jugo Zuko",
    "id": 7,
    "precio": 0.15,
    "cantidad": 496
  },
  {
    "nombre": "Yes Yes",
    "id": 2,
    "precio": 0.55,
    "cantidad": 994
  },
  {
    "nombre": "Vino Tinto Uvita",
    "id": 8,
    "precio": 10.0,
    "cantidad": 300
  },
  {
    "nombre": "Cerveza Brahma",
    "id": 9,
    "precio": 8.0,
    "cantidad": 397
  },
  {
    "nombre": "Fernet-Branca",
    "id": 12,
    "precio": 14.0,
    "cantidad": 426
  },
  {
    "nombre": "Pringles",
    "id": 1,
    "precio": 14.0,
    "cantidad": 996
  }
]